python_package_downloader/__init__.py
python_package_downloader-1.3.0.dist-info/METADATA
python_package_downloader-1.3.0.dist-info/WHEEL
python_package_downloader-1.3.0.dist-info/entry_points.txt
python_package_downloader-1.3.0.dist-info/top_level.txt
python_package_downloader-1.3.0.dist-info/RECORD
